{"iePublicationDate":null,"ieUpdateDate":"2024-06-17","ieControlNumber":"i10016777","mediaNumber":"M0110492","caption":{"name":"<I>374-3120</I> SUPPORT GP-RADIATOR <BR> S/N NN61-UP<BR>PART OF 388-1485 COOLING AR","language":"en","referencedCaptionParts":[{"partNumber":"3881485","orgCode":"CAT","ieSystemControlNumber":null,"disambiguation":false,"componentId":null},{"partNumber":"3743120","orgCode":"CAT","ieSystemControlNumber":null,"disambiguation":false,"componentId":null}],"orgCode":"CAT"},"groupPart":{"partNumber":"3743120","orgCode":"CAT","partName":{"name":"SUPPORT GP-RADIATOR","language":"en"},"modifier":{"name":" ","language":"en"},"serviceabilityIndicator":false,"alternatePartType":null,"imageIdentifiers":[],"hasAlternate":false,"isCCRPart":false},"smcsCodes":[{"code":"1353","description":{"name":"RADIATOR","language":"en"}}],"lineItems":[{"noteCodes":" ","partNumber":"2770750","orgCode":"CAT","partName":{"name":"PLATE","language":"en"},"serviceabilityIndicator":true,"partSequenceNumber":-999,"parentage":1,"quantity":"2","ieSystemControlNumber":null,"disambiguation":false,"mediaNumber":null,"componentId":null,"comments":"","referenceNumber":"1","graphicNumbers":["3"],"alternatePartType":null,"modifier":{"name":null,"language":"en"},"isCCRPart":false,"imageIdentifiers":["CM20230314-8ff6e-ffff8","CM20230314-43190-f3492","CM20230314-5e821-d60f5","CM20230314-cc76a-83892"],"hasAlternate":false},{"noteCodes":" ","partNumber":"3613890","orgCode":"CAT","partName":{"name":"LATCH AS","language":"en"},"serviceabilityIndicator":true,"partSequenceNumber":-998,"parentage":1,"quantity":"2","ieSystemControlNumber":null,"disambiguation":false,"mediaNumber":null,"componentId":null,"comments":"","referenceNumber":"2","graphicNumbers":["2","4"],"alternatePartType":null,"modifier":{"name":null,"language":"en"},"isCCRPart":false,"imageIdentifiers":["CM20230502-0e9fd-38bec","CM20230502-6dda1-55138","CM20230502-3306d-c0b16","CM20230502-02f82-2fe67"],"hasAlternate":false},{"noteCodes":" ","partNumber":"3881488","orgCode":"CAT","partName":{"name":"BAFFLE","language":"en"},"serviceabilityIndicator":true,"partSequenceNumber":-997,"parentage":1,"quantity":"1","ieSystemControlNumber":null,"disambiguation":false,"mediaNumber":null,"componentId":null,"comments":"","referenceNumber":"3","graphicNumbers":["4"],"alternatePartType":null,"modifier":{"name":null,"language":"en"},"isCCRPart":false,"imageIdentifiers":null,"hasAlternate":false},{"noteCodes":" ","partNumber":"3881489","orgCode":"CAT","partName":{"name":"PLATE","language":"en"},"serviceabilityIndicator":true,"partSequenceNumber":-996,"parentage":1,"quantity":"2","ieSystemControlNumber":null,"disambiguation":false,"mediaNumber":null,"componentId":null,"comments":"","referenceNumber":"4","graphicNumbers":["4"],"alternatePartType":null,"modifier":{"name":null,"language":"en"},"isCCRPart":false,"imageIdentifiers":null,"hasAlternate":false},{"noteCodes":" ","partNumber":"3907270","orgCode":"CAT","partName":{"name":"BAFFLE","language":"en"},"serviceabilityIndicator":true,"partSequenceNumber":-995,"parentage":1,"quantity":"1","ieSystemControlNumber":null,"disambiguation":false,"mediaNumber":null,"componentId":null,"comments":"","referenceNumber":"5","graphicNumbers":["5"],"alternatePartType":null,"modifier":{"name":null,"language":"en"},"isCCRPart":false,"imageIdentifiers":null,"hasAlternate":false},{"noteCodes":" ","partNumber":"3907271","orgCode":"CAT","partName":{"name":"PLATE","language":"en"},"serviceabilityIndicator":true,"partSequenceNumber":-994,"parentage":1,"quantity":"2","ieSystemControlNumber":null,"disambiguation":false,"mediaNumber":null,"componentId":null,"comments":"","referenceNumber":"6","graphicNumbers":["5"],"alternatePartType":null,"modifier":{"name":null,"language":"en"},"isCCRPart":false,"imageIdentifiers":null,"hasAlternate":false},{"noteCodes":" ","partNumber":"3961677","orgCode":"CAT","partName":{"name":"PLATE AS","language":"en"},"serviceabilityIndicator":true,"partSequenceNumber":-993,"parentage":1,"quantity":"1","ieSystemControlNumber":null,"disambiguation":false,"mediaNumber":null,"componentId":null,"comments":"","referenceNumber":"7","graphicNumbers":["3"],"alternatePartType":null,"modifier":{"name":null,"language":"en"},"isCCRPart":false,"imageIdentifiers":null,"hasAlternate":false},{"noteCodes":" ","partNumber":"3961678","orgCode":"CAT","partName":{"name":"PLATE AS","language":"en"},"serviceabilityIndicator":true,"partSequenceNumber":-992,"parentage":1,"quantity":"1","ieSystemControlNumber":null,"disambiguation":false,"mediaNumber":null,"componentId":null,"comments":"","referenceNumber":"8","graphicNumbers":["5"],"alternatePartType":null,"modifier":{"name":null,"language":"en"},"isCCRPart":false,"imageIdentifiers":null,"hasAlternate":false},{"noteCodes":" ","partNumber":"COMMENT","orgCode":"CAT","partName":{"name":null,"language":"en"},"serviceabilityIndicator":false,"partSequenceNumber":-991,"parentage":2,"quantity":" ","ieSystemControlNumber":null,"disambiguation":false,"mediaNumber":null,"componentId":null,"comments":"(EACH PLATE AS INCLUDES)","referenceNumber":" ","graphicNumbers":[" "],"alternatePartType":null,"modifier":{"name":null,"language":"en"},"isCCRPart":false,"imageIdentifiers":null,"hasAlternate":false},{"noteCodes":"M","partNumber":"3558941","orgCode":"CAT","partName":{"name":"NUT-WELD","language":"en"},"serviceabilityIndicator":true,"partSequenceNumber":-990,"parentage":2,"quantity":"4","ieSystemControlNumber":null,"disambiguation":false,"mediaNumber":null,"componentId":null,"comments":"","referenceNumber":" ","graphicNumbers":["5"],"alternatePartType":null,"modifier":{"name":"(M16X2-THD)","language":"en"},"isCCRPart":false,"imageIdentifiers":["CM20201012-a9c38-ad5c6","CM20201012-26136-28bd1","CM20201012-da3de-b149e","CM20201012-89d14-f851d"],"hasAlternate":false},{"noteCodes":" ","partNumber":"4203037","orgCode":"CAT","partName":{"name":"PLATE AS","language":"en"},"serviceabilityIndicator":true,"partSequenceNumber":-989,"parentage":1,"quantity":"2","ieSystemControlNumber":null,"disambiguation":false,"mediaNumber":null,"componentId":null,"comments":"","referenceNumber":"9","graphicNumbers":["3","5"],"alternatePartType":null,"modifier":{"name":null,"language":"en"},"isCCRPart":false,"imageIdentifiers":null,"hasAlternate":false},{"noteCodes":" ","partNumber":"COMMENT","orgCode":"CAT","partName":{"name":null,"language":"en"},"serviceabilityIndicator":false,"partSequenceNumber":-988,"parentage":2,"quantity":" ","ieSystemControlNumber":null,"disambiguation":false,"mediaNumber":null,"componentId":null,"comments":"(EACH INCLUDES)","referenceNumber":" ","graphicNumbers":[" "],"alternatePartType":null,"modifier":{"name":null,"language":"en"},"isCCRPart":false,"imageIdentifiers":null,"hasAlternate":false},{"noteCodes":"M","partNumber":"3558941","orgCode":"CAT","partName":{"name":"NUT-WELD","language":"en"},"serviceabilityIndicator":true,"partSequenceNumber":-987,"parentage":2,"quantity":"7","ieSystemControlNumber":null,"disambiguation":false,"mediaNumber":null,"componentId":null,"comments":"","referenceNumber":" ","graphicNumbers":["3","5"],"alternatePartType":null,"modifier":{"name":"(M16X2-THD)","language":"en"},"isCCRPart":false,"imageIdentifiers":["CM20201012-a9c38-ad5c6","CM20201012-26136-28bd1","CM20201012-da3de-b149e","CM20201012-89d14-f851d"],"hasAlternate":false},{"noteCodes":" ","partNumber":"4337128","orgCode":"CAT","partName":{"name":"SPACER","language":"en"},"serviceabilityIndicator":true,"partSequenceNumber":-986,"parentage":1,"quantity":"4","ieSystemControlNumber":null,"disambiguation":false,"mediaNumber":null,"componentId":null,"comments":"","referenceNumber":"10","graphicNumbers":["3"],"alternatePartType":null,"modifier":{"name":"(17X30X35-MM THK)","language":"en"},"isCCRPart":false,"imageIdentifiers":null,"hasAlternate":false},{"noteCodes":"C","partNumber":"4438179","orgCode":"CAT","partName":{"name":"PLATE AS","language":"en"},"serviceabilityIndicator":true,"partSequenceNumber":-985,"parentage":1,"quantity":"1","ieSystemControlNumber":null,"disambiguation":false,"mediaNumber":null,"componentId":null,"comments":"","referenceNumber":"11","graphicNumbers":["1"],"alternatePartType":null,"modifier":{"name":null,"language":"en"},"isCCRPart":false,"imageIdentifiers":null,"hasAlternate":false},{"noteCodes":" ","partNumber":"1F1609","orgCode":"CAT","partName":{"name":"SPACER","language":"en"},"serviceabilityIndicator":true,"partSequenceNumber":-983,"parentage":2,"quantity":"1","ieSystemControlNumber":null,"disambiguation":false,"mediaNumber":null,"componentId":null,"comments":"","referenceNumber":" ","graphicNumbers":["1"],"alternatePartType":null,"modifier":{"name":"(13.5X25.4X39.7-MM THK)","language":"en"},"isCCRPart":false,"imageIdentifiers":["CM20210104-90c67-2d1ab","CM20210503-eed4c-579d1","CM20210503-782f4-5d824","CM20210503-45bf6-a552d","CM20210503-4a2bb-fbb09"],"hasAlternate":false},{"noteCodes":" ","partNumber":"1V8284","orgCode":"CAT","partName":{"name":"HINGE","language":"en"},"serviceabilityIndicator":true,"partSequenceNumber":-982,"parentage":2,"quantity":"2","ieSystemControlNumber":null,"disambiguation":false,"mediaNumber":null,"componentId":null,"comments":"","referenceNumber":" ","graphicNumbers":["1"],"alternatePartType":null,"modifier":{"name":null,"language":"en"},"isCCRPart":false,"imageIdentifiers":["CM20220425-2d496-de834","CM20220425-48c13-817d8","CM20220425-eefd8-adb9f","CM20220425-90b79-fa279"],"hasAlternate":false},{"noteCodes":"M","partNumber":"8T3490","orgCode":"CAT","partName":{"name":"NUT-WELD","language":"en"},"serviceabilityIndicator":true,"partSequenceNumber":-981,"parentage":2,"quantity":"16","ieSystemControlNumber":null,"disambiguation":false,"mediaNumber":null,"componentId":null,"comments":"","referenceNumber":" ","graphicNumbers":["1"],"alternatePartType":null,"modifier":{"name":"(M10X1.5-THD)","language":"en"},"isCCRPart":false,"imageIdentifiers":["CM20210414-71313-9ded5","CM20210414-f5e52-effa9","CM20210414-0fb21-8839b","CM20210414-43071-229f2"],"hasAlternate":false},{"noteCodes":"M","partNumber":"8T3597","orgCode":"CAT","partName":{"name":"NUT-WELD","language":"en"},"serviceabilityIndicator":true,"partSequenceNumber":-980,"parentage":2,"quantity":"5","ieSystemControlNumber":null,"disambiguation":false,"mediaNumber":null,"componentId":null,"comments":"","referenceNumber":" ","graphicNumbers":["1"],"alternatePartType":null,"modifier":{"name":"(M12X1.75-THD)","language":"en"},"isCCRPart":false,"imageIdentifiers":["CM20210414-30214-f0d3e","CM20210414-c4188-a2d4e","CM20210414-f6b6b-2ab41","CM20210414-4c226-abc5b"],"hasAlternate":false},{"noteCodes":"M","partNumber":"8T3612","orgCode":"CAT","partName":{"name":"NUT-WELD","language":"en"},"serviceabilityIndicator":true,"partSequenceNumber":-979,"parentage":2,"quantity":"2","ieSystemControlNumber":null,"disambiguation":false,"mediaNumber":null,"componentId":null,"comments":"","referenceNumber":" ","graphicNumbers":["1"],"alternatePartType":null,"modifier":{"name":"(M8X1.25-THD)","language":"en"},"isCCRPart":false,"imageIdentifiers":["CM20210414-df290-187a5","CM20210414-aec0b-f0153","CM20210414-1b379-2eb4f","CM20210414-a6c75-bc255"],"hasAlternate":false},{"noteCodes":"M","partNumber":"9R2160","orgCode":"CAT","partName":{"name":"BOSS","language":"en"},"serviceabilityIndicator":true,"partSequenceNumber":-978,"parentage":2,"quantity":"4","ieSystemControlNumber":null,"disambiguation":false,"mediaNumber":null,"componentId":null,"comments":"","referenceNumber":" ","graphicNumbers":["1"],"alternatePartType":null,"modifier":{"name":"(M8X1.25X25-MM)","language":"en"},"isCCRPart":false,"imageIdentifiers":["CM20210414-ff68d-9f98b","CM20210414-f5989-1f715","CM20210414-885e4-6f9f7","CM20210414-a3de1-c0176"],"hasAlternate":false},{"noteCodes":"M","partNumber":"9R2613","orgCode":"CAT","partName":{"name":"BOSS-WELD","language":"en"},"serviceabilityIndicator":true,"partSequenceNumber":-977,"parentage":2,"quantity":"1","ieSystemControlNumber":null,"disambiguation":false,"mediaNumber":null,"componentId":null,"comments":"","referenceNumber":" ","graphicNumbers":["1"],"alternatePartType":null,"modifier":{"name":"(M10X1.5X25-MM)","language":"en"},"isCCRPart":false,"imageIdentifiers":["CM20210414-49070-e82ae","CM20210414-a8318-f21ff","CM20210414-6e256-36e5c","CM20210414-58716-81966"],"hasAlternate":false},{"noteCodes":" ","partNumber":"1984780","orgCode":"CAT","partName":{"name":"WASHER-HARD","language":"en"},"serviceabilityIndicator":true,"partSequenceNumber":-976,"parentage":2,"quantity":"1","ieSystemControlNumber":null,"disambiguation":false,"mediaNumber":null,"componentId":null,"comments":"","referenceNumber":" ","graphicNumbers":["1"],"alternatePartType":"K","modifier":{"name":"(17.5X32X8-MM THK)","language":"en"},"isCCRPart":false,"imageIdentifiers":["CM20210414-11af6-0f669","CM20210414-993df-87cb1","CM20210414-e06fd-df29c","CM20210414-d205e-81663"],"hasAlternate":true},{"noteCodes":" ","partNumber":"2598137","orgCode":"CAT","partName":{"name":"WASHER-HARD","language":"en"},"serviceabilityIndicator":true,"partSequenceNumber":-975,"parentage":2,"quantity":"3","ieSystemControlNumber":null,"disambiguation":false,"mediaNumber":null,"componentId":null,"comments":"","referenceNumber":" ","graphicNumbers":["1"],"alternatePartType":null,"modifier":{"name":"(17.5X32X22-MM THK)","language":"en"},"isCCRPart":false,"imageIdentifiers":["CM20201006-7b24c-c29a9","CM20201006-33842-69247","CM20201006-9557c-c16b4","CM20201006-96262-fefde"],"hasAlternate":false},{"noteCodes":"M","partNumber":"3558941","orgCode":"CAT","partName":{"name":"NUT-WELD","language":"en"},"serviceabilityIndicator":true,"partSequenceNumber":-974,"parentage":2,"quantity":"3","ieSystemControlNumber":null,"disambiguation":false,"mediaNumber":null,"componentId":null,"comments":"","referenceNumber":" ","graphicNumbers":["1"],"alternatePartType":null,"modifier":{"name":"(M16X2-THD)","language":"en"},"isCCRPart":false,"imageIdentifiers":["CM20201012-a9c38-ad5c6","CM20201012-26136-28bd1","CM20201012-da3de-b149e","CM20201012-89d14-f851d"],"hasAlternate":false},{"noteCodes":" ","partNumber":"2995177","orgCode":"CAT","partName":{"name":"PLATE","language":"en"},"serviceabilityIndicator":true,"partSequenceNumber":-973,"parentage":2,"quantity":"1","ieSystemControlNumber":null,"disambiguation":false,"mediaNumber":null,"componentId":null,"comments":"","referenceNumber":" ","graphicNumbers":["1"],"alternatePartType":null,"modifier":{"name":null,"language":"en"},"isCCRPart":false,"imageIdentifiers":null,"hasAlternate":false},{"noteCodes":"C","partNumber":"4438180","orgCode":"CAT","partName":{"name":"PLATE AS","language":"en"},"serviceabilityIndicator":true,"partSequenceNumber":-972,"parentage":1,"quantity":"1","ieSystemControlNumber":null,"disambiguation":false,"mediaNumber":null,"componentId":null,"comments":"","referenceNumber":"12","graphicNumbers":["4"],"alternatePartType":null,"modifier":{"name":null,"language":"en"},"isCCRPart":false,"imageIdentifiers":null,"hasAlternate":false},{"noteCodes":" ","partNumber":"1F1609","orgCode":"CAT","partName":{"name":"SPACER","language":"en"},"serviceabilityIndicator":true,"partSequenceNumber":-970,"parentage":2,"quantity":"1","ieSystemControlNumber":null,"disambiguation":false,"mediaNumber":null,"componentId":null,"comments":"","referenceNumber":" ","graphicNumbers":["4"],"alternatePartType":null,"modifier":{"name":"(13.5X25.4X39.7-MM THK)","language":"en"},"isCCRPart":false,"imageIdentifiers":["CM20210104-90c67-2d1ab","CM20210503-eed4c-579d1","CM20210503-782f4-5d824","CM20210503-45bf6-a552d","CM20210503-4a2bb-fbb09"],"hasAlternate":false},{"noteCodes":" ","partNumber":"1V8284","orgCode":"CAT","partName":{"name":"HINGE","language":"en"},"serviceabilityIndicator":true,"partSequenceNumber":-969,"parentage":2,"quantity":"2","ieSystemControlNumber":null,"disambiguation":false,"mediaNumber":null,"componentId":null,"comments":"","referenceNumber":" ","graphicNumbers":["4"],"alternatePartType":null,"modifier":{"name":null,"language":"en"},"isCCRPart":false,"imageIdentifiers":["CM20220425-2d496-de834","CM20220425-48c13-817d8","CM20220425-eefd8-adb9f","CM20220425-90b79-fa279"],"hasAlternate":false},{"noteCodes":" ","partNumber":"7T1099","orgCode":"CAT","partName":{"name":"LINK","language":"en"},"serviceabilityIndicator":true,"partSequenceNumber":-968,"parentage":2,"quantity":"3","ieSystemControlNumber":null,"disambiguation":false,"mediaNumber":null,"componentId":null,"comments":"","referenceNumber":" ","graphicNumbers":["4"],"alternatePartType":null,"modifier":{"name":null,"language":"en"},"isCCRPart":false,"imageIdentifiers":["CM20210414-ab10f-7c273","CM20210414-c91ba-8dce8","CM20210414-11ed0-666c9","CM20210414-04e20-0a1df"],"hasAlternate":false},{"noteCodes":"M","partNumber":"8T3490","orgCode":"CAT","partName":{"name":"NUT-WELD","language":"en"},"serviceabilityIndicator":true,"partSequenceNumber":-967,"parentage":2,"quantity":"15","ieSystemControlNumber":null,"disambiguation":false,"mediaNumber":null,"componentId":null,"comments":"","referenceNumber":" ","graphicNumbers":["4"],"alternatePartType":null,"modifier":{"name":"(M10X1.5-THD)","language":"en"},"isCCRPart":false,"imageIdentifiers":["CM20210414-71313-9ded5","CM20210414-f5e52-effa9","CM20210414-0fb21-8839b","CM20210414-43071-229f2"],"hasAlternate":false},{"noteCodes":"M","partNumber":"8T3597","orgCode":"CAT","partName":{"name":"NUT-WELD","language":"en"},"serviceabilityIndicator":true,"partSequenceNumber":-966,"parentage":2,"quantity":"5","ieSystemControlNumber":null,"disambiguation":false,"mediaNumber":null,"componentId":null,"comments":"","referenceNumber":" ","graphicNumbers":["4"],"alternatePartType":null,"modifier":{"name":"(M12X1.75-THD)","language":"en"},"isCCRPart":false,"imageIdentifiers":["CM20210414-30214-f0d3e","CM20210414-c4188-a2d4e","CM20210414-f6b6b-2ab41","CM20210414-4c226-abc5b"],"hasAlternate":false},{"noteCodes":"M","partNumber":"8T3612","orgCode":"CAT","partName":{"name":"NUT-WELD","language":"en"},"serviceabilityIndicator":true,"partSequenceNumber":-965,"parentage":2,"quantity":"8","ieSystemControlNumber":null,"disambiguation":false,"mediaNumber":null,"componentId":null,"comments":"","referenceNumber":" ","graphicNumbers":["4"],"alternatePartType":null,"modifier":{"name":"(M8X1.25-THD)","language":"en"},"isCCRPart":false,"imageIdentifiers":["CM20210414-df290-187a5","CM20210414-aec0b-f0153","CM20210414-1b379-2eb4f","CM20210414-a6c75-bc255"],"hasAlternate":false},{"noteCodes":"M","partNumber":"9R2160","orgCode":"CAT","partName":{"name":"BOSS","language":"en"},"serviceabilityIndicator":true,"partSequenceNumber":-964,"parentage":2,"quantity":"4","ieSystemControlNumber":null,"disambiguation":false,"mediaNumber":null,"componentId":null,"comments":"","referenceNumber":" ","graphicNumbers":["4"],"alternatePartType":null,"modifier":{"name":"(M8X1.25X25-MM)","language":"en"},"isCCRPart":false,"imageIdentifiers":["CM20210414-ff68d-9f98b","CM20210414-f5989-1f715","CM20210414-885e4-6f9f7","CM20210414-a3de1-c0176"],"hasAlternate":false},{"noteCodes":"M","partNumber":"9R2613","orgCode":"CAT","partName":{"name":"BOSS-WELD","language":"en"},"serviceabilityIndicator":true,"partSequenceNumber":-963,"parentage":2,"quantity":"1","ieSystemControlNumber":null,"disambiguation":false,"mediaNumber":null,"componentId":null,"comments":"","referenceNumber":" ","graphicNumbers":["4"],"alternatePartType":null,"modifier":{"name":"(M10X1.5X25-MM)","language":"en"},"isCCRPart":false,"imageIdentifiers":["CM20210414-49070-e82ae","CM20210414-a8318-f21ff","CM20210414-6e256-36e5c","CM20210414-58716-81966"],"hasAlternate":false},{"noteCodes":"M","partNumber":"9R2821","orgCode":"CAT","partName":{"name":"BOSS","language":"en"},"serviceabilityIndicator":true,"partSequenceNumber":-962,"parentage":2,"quantity":"1","ieSystemControlNumber":null,"disambiguation":false,"mediaNumber":null,"componentId":null,"comments":"","referenceNumber":" ","graphicNumbers":["4"],"alternatePartType":null,"modifier":{"name":"(M10X1.5X15-MM)","language":"en"},"isCCRPart":false,"imageIdentifiers":["CM20200609-c2070-71c41","CM20200609-32bbb-f6b4e","CM20200609-c5786-4030f","CM20200609-4614d-9dfe1"],"hasAlternate":false},{"noteCodes":" ","partNumber":"1984780","orgCode":"CAT","partName":{"name":"WASHER-HARD","language":"en"},"serviceabilityIndicator":true,"partSequenceNumber":-961,"parentage":2,"quantity":"1","ieSystemControlNumber":null,"disambiguation":false,"mediaNumber":null,"componentId":null,"comments":"","referenceNumber":" ","graphicNumbers":["4"],"alternatePartType":"K","modifier":{"name":"(17.5X32X8-MM THK)","language":"en"},"isCCRPart":false,"imageIdentifiers":["CM20210414-11af6-0f669","CM20210414-993df-87cb1","CM20210414-e06fd-df29c","CM20210414-d205e-81663"],"hasAlternate":true},{"noteCodes":" ","partNumber":"2598137","orgCode":"CAT","partName":{"name":"WASHER-HARD","language":"en"},"serviceabilityIndicator":true,"partSequenceNumber":-960,"parentage":2,"quantity":"3","ieSystemControlNumber":null,"disambiguation":false,"mediaNumber":null,"componentId":null,"comments":"","referenceNumber":" ","graphicNumbers":["4"],"alternatePartType":null,"modifier":{"name":"(17.5X32X22-MM THK)","language":"en"},"isCCRPart":false,"imageIdentifiers":["CM20201006-7b24c-c29a9","CM20201006-33842-69247","CM20201006-9557c-c16b4","CM20201006-96262-fefde"],"hasAlternate":false},{"noteCodes":"M","partNumber":"3558941","orgCode":"CAT","partName":{"name":"NUT-WELD","language":"en"},"serviceabilityIndicator":true,"partSequenceNumber":-959,"parentage":2,"quantity":"3","ieSystemControlNumber":null,"disambiguation":false,"mediaNumber":null,"componentId":null,"comments":"","referenceNumber":" ","graphicNumbers":["4"],"alternatePartType":null,"modifier":{"name":"(M16X2-THD)","language":"en"},"isCCRPart":false,"imageIdentifiers":["CM20201012-a9c38-ad5c6","CM20201012-26136-28bd1","CM20201012-da3de-b149e","CM20201012-89d14-f851d"],"hasAlternate":false},{"noteCodes":" ","partNumber":"2995177","orgCode":"CAT","partName":{"name":"PLATE","language":"en"},"serviceabilityIndicator":true,"partSequenceNumber":-958,"parentage":2,"quantity":"1","ieSystemControlNumber":null,"disambiguation":false,"mediaNumber":null,"componentId":null,"comments":"","referenceNumber":" ","graphicNumbers":["4"],"alternatePartType":null,"modifier":{"name":null,"language":"en"},"isCCRPart":false,"imageIdentifiers":null,"hasAlternate":false},{"noteCodes":"C","partNumber":"4438181","orgCode":"CAT","partName":{"name":"PLATE","language":"en"},"serviceabilityIndicator":true,"partSequenceNumber":-957,"parentage":1,"quantity":"2","ieSystemControlNumber":null,"disambiguation":false,"mediaNumber":null,"componentId":null,"comments":"","referenceNumber":"13","graphicNumbers":["2","4"],"alternatePartType":null,"modifier":{"name":null,"language":"en"},"isCCRPart":false,"imageIdentifiers":null,"hasAlternate":false},{"noteCodes":"C","partNumber":"4438182","orgCode":"CAT","partName":{"name":"BRACKET AS","language":"en"},"serviceabilityIndicator":true,"partSequenceNumber":-956,"parentage":1,"quantity":"1","ieSystemControlNumber":null,"disambiguation":false,"mediaNumber":null,"componentId":null,"comments":"","referenceNumber":"14","graphicNumbers":["2"],"alternatePartType":null,"modifier":{"name":null,"language":"en"},"isCCRPart":false,"imageIdentifiers":null,"hasAlternate":false},{"noteCodes":"C","partNumber":"4438183","orgCode":"CAT","partName":{"name":"BRACKET AS","language":"en"},"serviceabilityIndicator":true,"partSequenceNumber":-955,"parentage":1,"quantity":"1","ieSystemControlNumber":null,"disambiguation":false,"mediaNumber":null,"componentId":null,"comments":"","referenceNumber":"15","graphicNumbers":["5"],"alternatePartType":null,"modifier":{"name":null,"language":"en"},"isCCRPart":false,"imageIdentifiers":null,"hasAlternate":false},{"noteCodes":" ","partNumber":"COMMENT","orgCode":"CAT","partName":{"name":null,"language":"en"},"serviceabilityIndicator":false,"partSequenceNumber":-954,"parentage":2,"quantity":" ","ieSystemControlNumber":null,"disambiguation":false,"mediaNumber":null,"componentId":null,"comments":"(EACH BRACKET AS INCLUDES)","referenceNumber":" ","graphicNumbers":[" "],"alternatePartType":null,"modifier":{"name":null,"language":"en"},"isCCRPart":false,"imageIdentifiers":null,"hasAlternate":false},{"noteCodes":"M","partNumber":"8T3490","orgCode":"CAT","partName":{"name":"NUT-WELD","language":"en"},"serviceabilityIndicator":true,"partSequenceNumber":-953,"parentage":2,"quantity":"1","ieSystemControlNumber":null,"disambiguation":false,"mediaNumber":null,"componentId":null,"comments":"","referenceNumber":" ","graphicNumbers":["5"],"alternatePartType":null,"modifier":{"name":"(M10X1.5-THD)","language":"en"},"isCCRPart":false,"imageIdentifiers":["CM20210414-71313-9ded5","CM20210414-f5e52-effa9","CM20210414-0fb21-8839b","CM20210414-43071-229f2"],"hasAlternate":false},{"noteCodes":"M","partNumber":"3558941","orgCode":"CAT","partName":{"name":"NUT-WELD","language":"en"},"serviceabilityIndicator":true,"partSequenceNumber":-952,"parentage":2,"quantity":"2","ieSystemControlNumber":null,"disambiguation":false,"mediaNumber":null,"componentId":null,"comments":"","referenceNumber":" ","graphicNumbers":["5"],"alternatePartType":null,"modifier":{"name":"(M16X2-THD)","language":"en"},"isCCRPart":false,"imageIdentifiers":["CM20201012-a9c38-ad5c6","CM20201012-26136-28bd1","CM20201012-da3de-b149e","CM20201012-89d14-f851d"],"hasAlternate":false},{"noteCodes":"C","partNumber":"6131608","orgCode":"CAT","partName":{"name":"GRILL AS","language":"en"},"serviceabilityIndicator":true,"partSequenceNumber":-951,"parentage":1,"quantity":"1","ieSystemControlNumber":null,"disambiguation":false,"mediaNumber":null,"componentId":null,"comments":"","referenceNumber":"16","graphicNumbers":["1"],"alternatePartType":null,"modifier":{"name":null,"language":"en"},"isCCRPart":false,"imageIdentifiers":null,"hasAlternate":false},{"noteCodes":"M","partNumber":"8T3490","orgCode":"CAT","partName":{"name":"NUT-WELD","language":"en"},"serviceabilityIndicator":true,"partSequenceNumber":-950,"parentage":2,"quantity":"3","ieSystemControlNumber":null,"disambiguation":false,"mediaNumber":null,"componentId":null,"comments":"","referenceNumber":" ","graphicNumbers":["1"],"alternatePartType":null,"modifier":{"name":"(M10X1.5-THD)","language":"en"},"isCCRPart":false,"imageIdentifiers":["CM20210414-71313-9ded5","CM20210414-f5e52-effa9","CM20210414-0fb21-8839b","CM20210414-43071-229f2"],"hasAlternate":false},{"noteCodes":" ","partNumber":"4580287","orgCode":"CAT","partName":{"name":"PLATE","language":"en"},"serviceabilityIndicator":true,"partSequenceNumber":-949,"parentage":1,"quantity":"2","ieSystemControlNumber":null,"disambiguation":false,"mediaNumber":null,"componentId":null,"comments":"","referenceNumber":"17","graphicNumbers":["4"],"alternatePartType":null,"modifier":{"name":null,"language":"en"},"isCCRPart":false,"imageIdentifiers":null,"hasAlternate":false},{"noteCodes":" ","partNumber":"4763279","orgCode":"CAT","partName":{"name":"PLATE AS","language":"en"},"serviceabilityIndicator":true,"partSequenceNumber":-948,"parentage":1,"quantity":"1","ieSystemControlNumber":null,"disambiguation":false,"mediaNumber":null,"componentId":null,"comments":"","referenceNumber":"18","graphicNumbers":["4"],"alternatePartType":null,"modifier":{"name":null,"language":"en"},"isCCRPart":false,"imageIdentifiers":null,"hasAlternate":false},{"noteCodes":"M","partNumber":"8T3490","orgCode":"CAT","partName":{"name":"NUT-WELD","language":"en"},"serviceabilityIndicator":true,"partSequenceNumber":-947,"parentage":2,"quantity":"8","ieSystemControlNumber":null,"disambiguation":false,"mediaNumber":null,"componentId":null,"comments":"","referenceNumber":" ","graphicNumbers":["4"],"alternatePartType":null,"modifier":{"name":"(M10X1.5-THD)","language":"en"},"isCCRPart":false,"imageIdentifiers":["CM20210414-71313-9ded5","CM20210414-f5e52-effa9","CM20210414-0fb21-8839b","CM20210414-43071-229f2"],"hasAlternate":false},{"noteCodes":"M","partNumber":"8T3597","orgCode":"CAT","partName":{"name":"NUT-WELD","language":"en"},"serviceabilityIndicator":true,"partSequenceNumber":-946,"parentage":2,"quantity":"2","ieSystemControlNumber":null,"disambiguation":false,"mediaNumber":null,"componentId":null,"comments":"","referenceNumber":" ","graphicNumbers":["4"],"alternatePartType":null,"modifier":{"name":"(M12X1.75-THD)","language":"en"},"isCCRPart":false,"imageIdentifiers":["CM20210414-30214-f0d3e","CM20210414-c4188-a2d4e","CM20210414-f6b6b-2ab41","CM20210414-4c226-abc5b"],"hasAlternate":false},{"noteCodes":"M","partNumber":"3558941","orgCode":"CAT","partName":{"name":"NUT-WELD","language":"en"},"serviceabilityIndicator":true,"partSequenceNumber":-945,"parentage":2,"quantity":"4","ieSystemControlNumber":null,"disambiguation":false,"mediaNumber":null,"componentId":null,"comments":"","referenceNumber":" ","graphicNumbers":["4"],"alternatePartType":null,"modifier":{"name":"(M16X2-THD)","language":"en"},"isCCRPart":false,"imageIdentifiers":["CM20201012-a9c38-ad5c6","CM20201012-26136-28bd1","CM20201012-da3de-b149e","CM20201012-89d14-f851d"],"hasAlternate":false},{"noteCodes":"C","partNumber":"4438199","orgCode":"CAT","partName":{"name":"BRACKET AS","language":"en"},"serviceabilityIndicator":true,"partSequenceNumber":-944,"parentage":1,"quantity":"1","ieSystemControlNumber":null,"disambiguation":false,"mediaNumber":null,"componentId":null,"comments":"","referenceNumber":"19","graphicNumbers":["3"],"alternatePartType":null,"modifier":{"name":null,"language":"en"},"isCCRPart":false,"imageIdentifiers":null,"hasAlternate":false},{"noteCodes":"C","partNumber":"4438198","orgCode":"CAT","partName":{"name":"BRACKET AS","language":"en"},"serviceabilityIndicator":true,"partSequenceNumber":-943,"parentage":1,"quantity":"1","ieSystemControlNumber":null,"disambiguation":false,"mediaNumber":null,"componentId":null,"comments":"","referenceNumber":"20","graphicNumbers":["5"],"alternatePartType":null,"modifier":{"name":null,"language":"en"},"isCCRPart":false,"imageIdentifiers":null,"hasAlternate":false},{"noteCodes":" ","partNumber":"COMMENT","orgCode":"CAT","partName":{"name":null,"language":"en"},"serviceabilityIndicator":false,"partSequenceNumber":-942,"parentage":2,"quantity":" ","ieSystemControlNumber":null,"disambiguation":false,"mediaNumber":null,"componentId":null,"comments":"(EACH BRACKET AS INCLUDES)","referenceNumber":" ","graphicNumbers":[" "],"alternatePartType":null,"modifier":{"name":null,"language":"en"},"isCCRPart":false,"imageIdentifiers":null,"hasAlternate":false},{"noteCodes":" ","partNumber":"1F1609","orgCode":"CAT","partName":{"name":"SPACER","language":"en"},"serviceabilityIndicator":true,"partSequenceNumber":-941,"parentage":2,"quantity":"1","ieSystemControlNumber":null,"disambiguation":false,"mediaNumber":null,"componentId":null,"comments":"","referenceNumber":" ","graphicNumbers":["5"],"alternatePartType":null,"modifier":{"name":"(13.5X25.4X39.7-MM THK)","language":"en"},"isCCRPart":false,"imageIdentifiers":["CM20210104-90c67-2d1ab","CM20210503-eed4c-579d1","CM20210503-782f4-5d824","CM20210503-45bf6-a552d","CM20210503-4a2bb-fbb09"],"hasAlternate":false},{"noteCodes":"M","partNumber":"8T3490","orgCode":"CAT","partName":{"name":"NUT-WELD","language":"en"},"serviceabilityIndicator":true,"partSequenceNumber":-940,"parentage":2,"quantity":"3","ieSystemControlNumber":null,"disambiguation":false,"mediaNumber":null,"componentId":null,"comments":"","referenceNumber":" ","graphicNumbers":["5"],"alternatePartType":null,"modifier":{"name":"(M10X1.5-THD)","language":"en"},"isCCRPart":false,"imageIdentifiers":["CM20210414-71313-9ded5","CM20210414-f5e52-effa9","CM20210414-0fb21-8839b","CM20210414-43071-229f2"],"hasAlternate":false},{"noteCodes":" ","partNumber":"4829169","orgCode":"CAT","partName":{"name":"PLATE AS","language":"en"},"serviceabilityIndicator":true,"partSequenceNumber":-939,"parentage":1,"quantity":"1","ieSystemControlNumber":null,"disambiguation":false,"mediaNumber":null,"componentId":null,"comments":"","referenceNumber":"21","graphicNumbers":["1"],"alternatePartType":null,"modifier":{"name":null,"language":"en"},"isCCRPart":false,"imageIdentifiers":null,"hasAlternate":false},{"noteCodes":"M","partNumber":"8T3490","orgCode":"CAT","partName":{"name":"NUT-WELD","language":"en"},"serviceabilityIndicator":true,"partSequenceNumber":-938,"parentage":2,"quantity":"5","ieSystemControlNumber":null,"disambiguation":false,"mediaNumber":null,"componentId":null,"comments":"","referenceNumber":" ","graphicNumbers":["1"],"alternatePartType":null,"modifier":{"name":"(M10X1.5-THD)","language":"en"},"isCCRPart":false,"imageIdentifiers":["CM20210414-71313-9ded5","CM20210414-f5e52-effa9","CM20210414-0fb21-8839b","CM20210414-43071-229f2"],"hasAlternate":false},{"noteCodes":" ","partNumber":"4781319","orgCode":"CAT","partName":{"name":"PLATE AS","language":"en"},"serviceabilityIndicator":true,"partSequenceNumber":-937,"parentage":1,"quantity":"2","ieSystemControlNumber":null,"disambiguation":false,"mediaNumber":null,"componentId":null,"comments":"","referenceNumber":"22","graphicNumbers":["3","4"],"alternatePartType":null,"modifier":{"name":null,"language":"en"},"isCCRPart":false,"imageIdentifiers":null,"hasAlternate":false},{"noteCodes":" ","partNumber":"COMMENT","orgCode":"CAT","partName":{"name":null,"language":"en"},"serviceabilityIndicator":false,"partSequenceNumber":-936,"parentage":2,"quantity":" ","ieSystemControlNumber":null,"disambiguation":false,"mediaNumber":null,"componentId":null,"comments":"(EACH INCLUDES)","referenceNumber":" ","graphicNumbers":[" "],"alternatePartType":null,"modifier":{"name":null,"language":"en"},"isCCRPart":false,"imageIdentifiers":null,"hasAlternate":false},{"noteCodes":"M","partNumber":"8T3490","orgCode":"CAT","partName":{"name":"NUT-WELD","language":"en"},"serviceabilityIndicator":true,"partSequenceNumber":-935,"parentage":2,"quantity":"2","ieSystemControlNumber":null,"disambiguation":false,"mediaNumber":null,"componentId":null,"comments":"","referenceNumber":" ","graphicNumbers":["3","4"],"alternatePartType":null,"modifier":{"name":"(M10X1.5-THD)","language":"en"},"isCCRPart":false,"imageIdentifiers":["CM20210414-71313-9ded5","CM20210414-f5e52-effa9","CM20210414-0fb21-8839b","CM20210414-43071-229f2"],"hasAlternate":false},{"noteCodes":" ","partNumber":"4781935","orgCode":"CAT","partName":{"name":"BRACKET AS","language":"en"},"serviceabilityIndicator":true,"partSequenceNumber":-934,"parentage":1,"quantity":"1","ieSystemControlNumber":null,"disambiguation":false,"mediaNumber":null,"componentId":null,"comments":"","referenceNumber":"23","graphicNumbers":["3"],"alternatePartType":null,"modifier":{"name":null,"language":"en"},"isCCRPart":false,"imageIdentifiers":null,"hasAlternate":false},{"noteCodes":"M","partNumber":"8T3490","orgCode":"CAT","partName":{"name":"NUT-WELD","language":"en"},"serviceabilityIndicator":true,"partSequenceNumber":-933,"parentage":2,"quantity":"2","ieSystemControlNumber":null,"disambiguation":false,"mediaNumber":null,"componentId":null,"comments":"","referenceNumber":" ","graphicNumbers":["3"],"alternatePartType":null,"modifier":{"name":"(M10X1.5-THD)","language":"en"},"isCCRPart":false,"imageIdentifiers":["CM20210414-71313-9ded5","CM20210414-f5e52-effa9","CM20210414-0fb21-8839b","CM20210414-43071-229f2"],"hasAlternate":false},{"noteCodes":" ","partNumber":"4833712","orgCode":"CAT","partName":{"name":"PLATE AS","language":"en"},"serviceabilityIndicator":true,"partSequenceNumber":-932,"parentage":1,"quantity":"1","ieSystemControlNumber":null,"disambiguation":false,"mediaNumber":null,"componentId":null,"comments":"","referenceNumber":"24","graphicNumbers":["4"],"alternatePartType":null,"modifier":{"name":null,"language":"en"},"isCCRPart":false,"imageIdentifiers":null,"hasAlternate":false},{"noteCodes":" ","partNumber":"7T1099","orgCode":"CAT","partName":{"name":"LINK","language":"en"},"serviceabilityIndicator":true,"partSequenceNumber":-931,"parentage":2,"quantity":"2","ieSystemControlNumber":null,"disambiguation":false,"mediaNumber":null,"componentId":null,"comments":"","referenceNumber":" ","graphicNumbers":["4"],"alternatePartType":null,"modifier":{"name":null,"language":"en"},"isCCRPart":false,"imageIdentifiers":["CM20210414-ab10f-7c273","CM20210414-c91ba-8dce8","CM20210414-11ed0-666c9","CM20210414-04e20-0a1df"],"hasAlternate":false},{"noteCodes":"M","partNumber":"8T3490","orgCode":"CAT","partName":{"name":"NUT-WELD","language":"en"},"serviceabilityIndicator":true,"partSequenceNumber":-930,"parentage":2,"quantity":"1","ieSystemControlNumber":null,"disambiguation":false,"mediaNumber":null,"componentId":null,"comments":"","referenceNumber":" ","graphicNumbers":["4"],"alternatePartType":null,"modifier":{"name":"(M10X1.5-THD)","language":"en"},"isCCRPart":false,"imageIdentifiers":["CM20210414-71313-9ded5","CM20210414-f5e52-effa9","CM20210414-0fb21-8839b","CM20210414-43071-229f2"],"hasAlternate":false},{"noteCodes":"M","partNumber":"8T3612","orgCode":"CAT","partName":{"name":"NUT-WELD","language":"en"},"serviceabilityIndicator":true,"partSequenceNumber":-929,"parentage":2,"quantity":"4","ieSystemControlNumber":null,"disambiguation":false,"mediaNumber":null,"componentId":null,"comments":"","referenceNumber":" ","graphicNumbers":["4"],"alternatePartType":null,"modifier":{"name":"(M8X1.25-THD)","language":"en"},"isCCRPart":false,"imageIdentifiers":["CM20210414-df290-187a5","CM20210414-aec0b-f0153","CM20210414-1b379-2eb4f","CM20210414-a6c75-bc255"],"hasAlternate":false},{"noteCodes":"M","partNumber":"9C7929","orgCode":"CAT","partName":{"name":"BOSS","language":"en"},"serviceabilityIndicator":true,"partSequenceNumber":-928,"parentage":2,"quantity":"2","ieSystemControlNumber":null,"disambiguation":false,"mediaNumber":null,"componentId":null,"comments":"","referenceNumber":" ","graphicNumbers":["4"],"alternatePartType":null,"modifier":{"name":"(M10X1.5X20-MM)","language":"en"},"isCCRPart":false,"imageIdentifiers":["CM20201125-d374b-c0fd1","CM20201125-eeec9-92b42","CM20201125-56f0d-cb328","CM20201125-c1b5e-51385"],"hasAlternate":false},{"noteCodes":"M","partNumber":"9R3761","orgCode":"CAT","partName":{"name":"BOSS","language":"en"},"serviceabilityIndicator":true,"partSequenceNumber":-927,"parentage":2,"quantity":"1","ieSystemControlNumber":null,"disambiguation":false,"mediaNumber":null,"componentId":null,"comments":"","referenceNumber":" ","graphicNumbers":["4"],"alternatePartType":null,"modifier":{"name":"(M10X1.5X51-MM)","language":"en"},"isCCRPart":false,"imageIdentifiers":["CM20210503-1ee55-1c7db","CM20210503-9e31f-e38ad","CM20210503-7da55-e89d4","CM20210503-05334-c13cf"],"hasAlternate":false},{"noteCodes":"M","partNumber":"3558941","orgCode":"CAT","partName":{"name":"NUT-WELD","language":"en"},"serviceabilityIndicator":true,"partSequenceNumber":-926,"parentage":2,"quantity":"4","ieSystemControlNumber":null,"disambiguation":false,"mediaNumber":null,"componentId":null,"comments":"","referenceNumber":" ","graphicNumbers":["4"],"alternatePartType":null,"modifier":{"name":"(M16X2-THD)","language":"en"},"isCCRPart":false,"imageIdentifiers":["CM20201012-a9c38-ad5c6","CM20201012-26136-28bd1","CM20201012-da3de-b149e","CM20201012-89d14-f851d"],"hasAlternate":false},{"noteCodes":" ","partNumber":"4833713","orgCode":"CAT","partName":{"name":"BRACKET AS","language":"en"},"serviceabilityIndicator":true,"partSequenceNumber":-925,"parentage":1,"quantity":"2","ieSystemControlNumber":null,"disambiguation":false,"mediaNumber":null,"componentId":null,"comments":"","referenceNumber":"25","graphicNumbers":["4","5"],"alternatePartType":null,"modifier":{"name":null,"language":"en"},"isCCRPart":false,"imageIdentifiers":null,"hasAlternate":false},{"noteCodes":" ","partNumber":"COMMENT","orgCode":"CAT","partName":{"name":null,"language":"en"},"serviceabilityIndicator":false,"partSequenceNumber":-924,"parentage":2,"quantity":" ","ieSystemControlNumber":null,"disambiguation":false,"mediaNumber":null,"componentId":null,"comments":"(EACH INCLUDES)","referenceNumber":" ","graphicNumbers":[" "],"alternatePartType":null,"modifier":{"name":null,"language":"en"},"isCCRPart":false,"imageIdentifiers":null,"hasAlternate":false},{"noteCodes":" ","partNumber":"6H7062","orgCode":"CAT","partName":{"name":"SPACER","language":"en"},"serviceabilityIndicator":true,"partSequenceNumber":-923,"parentage":2,"quantity":"2","ieSystemControlNumber":null,"disambiguation":false,"mediaNumber":null,"componentId":null,"comments":"","referenceNumber":" ","graphicNumbers":["4","5"],"alternatePartType":null,"modifier":{"name":"(13.5X25X19-MM THK)","language":"en"},"isCCRPart":false,"imageIdentifiers":["CM20180404-39513-50297"],"hasAlternate":false},{"noteCodes":"M","partNumber":"8T3490","orgCode":"CAT","partName":{"name":"NUT-WELD","language":"en"},"serviceabilityIndicator":true,"partSequenceNumber":-922,"parentage":2,"quantity":"2","ieSystemControlNumber":null,"disambiguation":false,"mediaNumber":null,"componentId":null,"comments":"","referenceNumber":" ","graphicNumbers":["4","5"],"alternatePartType":null,"modifier":{"name":"(M10X1.5-THD)","language":"en"},"isCCRPart":false,"imageIdentifiers":["CM20210414-71313-9ded5","CM20210414-f5e52-effa9","CM20210414-0fb21-8839b","CM20210414-43071-229f2"],"hasAlternate":false},{"noteCodes":"M","partNumber":"1146099","orgCode":"CAT","partName":{"name":"BOLT","language":"en"},"serviceabilityIndicator":true,"partSequenceNumber":-921,"parentage":1,"quantity":"8","ieSystemControlNumber":null,"disambiguation":false,"mediaNumber":null,"componentId":null,"comments":"","referenceNumber":"26","graphicNumbers":["2","3"],"alternatePartType":null,"modifier":{"name":"(M24X3X80-MM)","language":"en"},"isCCRPart":false,"imageIdentifiers":["CM20201026-93291-c74fb","CM20201026-cf644-1641c","CM20201026-11686-6f915","CM20201026-4f538-907f9"],"hasAlternate":false},{"noteCodes":"M","partNumber":"1765311","orgCode":"CAT","partName":{"name":"LOCKNUT","language":"en"},"serviceabilityIndicator":true,"partSequenceNumber":-920,"parentage":1,"quantity":"4","ieSystemControlNumber":null,"disambiguation":false,"mediaNumber":null,"componentId":null,"comments":"","referenceNumber":"27","graphicNumbers":["3"],"alternatePartType":null,"modifier":{"name":"(M16X2-THD)","language":"en"},"isCCRPart":false,"imageIdentifiers":["CM20180124-55592-09958","CM20180124-55592-36464","CM20180124-55592-35622","CM20180124-55592-41375"],"hasAlternate":false},{"noteCodes":" ","partNumber":"1984777","orgCode":"CAT","partName":{"name":"WASHER-HARD","language":"en"},"serviceabilityIndicator":true,"partSequenceNumber":-919,"parentage":1,"quantity":"19","ieSystemControlNumber":null,"disambiguation":false,"mediaNumber":null,"componentId":null,"comments":"","referenceNumber":"28","graphicNumbers":["1","2","3"],"alternatePartType":"K","modifier":{"name":"(11X25X10-MM THK)","language":"en"},"isCCRPart":false,"imageIdentifiers":["CM20210414-ffd1b-48764","CM20210414-bf689-de271","CM20210414-ea5df-565b8","CM20210414-d4d4b-4b3bf"],"hasAlternate":true},{"noteCodes":" ","partNumber":"1984778","orgCode":"CAT","partName":{"name":"WASHER-HARD","language":"en"},"serviceabilityIndicator":true,"partSequenceNumber":-918,"parentage":1,"quantity":"6","ieSystemControlNumber":null,"disambiguation":false,"mediaNumber":null,"componentId":null,"comments":"","referenceNumber":"29","graphicNumbers":["2"],"alternatePartType":"K","modifier":{"name":"(13.5X30X12-MM THK)","language":"en"},"isCCRPart":false,"imageIdentifiers":["CM20210414-eff69-2298a","CM20210414-b17d3-09389","CM20210414-265d4-4b657","CM20210414-3126e-73817"],"hasAlternate":true},{"noteCodes":"C","partNumber":"1984780","orgCode":"CAT","partName":{"name":"WASHER-HARD","language":"en"},"serviceabilityIndicator":true,"partSequenceNumber":-917,"parentage":1,"quantity":"8","ieSystemControlNumber":null,"disambiguation":false,"mediaNumber":null,"componentId":null,"comments":"","referenceNumber":"30","graphicNumbers":["3"],"alternatePartType":"K","modifier":{"name":"(17.5X32X8-MM THK)","language":"en"},"isCCRPart":false,"imageIdentifiers":["CM20210414-11af6-0f669","CM20210414-993df-87cb1","CM20210414-e06fd-df29c","CM20210414-d205e-81663"],"hasAlternate":true},{"noteCodes":" ","partNumber":"2673507","orgCode":"CAT","partName":{"name":"WASHER-HARD","language":"en"},"serviceabilityIndicator":true,"partSequenceNumber":-916,"parentage":1,"quantity":"8","ieSystemControlNumber":null,"disambiguation":false,"mediaNumber":null,"componentId":null,"comments":"","referenceNumber":"31","graphicNumbers":["2","3"],"alternatePartType":"K","modifier":{"name":"(26X47X12-MM THK)","language":"en"},"isCCRPart":false,"imageIdentifiers":["CM20200811-54fed-10bc8","CM20200811-9bb45-e2a75","CM20200811-454a9-d6a94","CM20200811-77b59-2ac7b"],"hasAlternate":true},{"noteCodes":"M","partNumber":"2065143","orgCode":"CAT","partName":{"name":"BOLT","language":"en"},"serviceabilityIndicator":true,"partSequenceNumber":-915,"parentage":1,"quantity":"2","ieSystemControlNumber":null,"disambiguation":false,"mediaNumber":null,"componentId":null,"comments":"","referenceNumber":"32","graphicNumbers":["2","5"],"alternatePartType":null,"modifier":{"name":"(M12X1.75X50-MM)","language":"en"},"isCCRPart":false,"imageIdentifiers":["CM20201002-160f9-c5b0d","CM20201002-7a4b1-b25a4","CM20201002-0bac3-7f0d8","CM20201002-e64a9-ee116"],"hasAlternate":false},{"noteCodes":"C","partNumber":"2678821","orgCode":"CAT","partName":{"name":"WASHER","language":"en"},"serviceabilityIndicator":true,"partSequenceNumber":-914,"parentage":1,"quantity":"28","ieSystemControlNumber":null,"disambiguation":false,"mediaNumber":null,"componentId":null,"comments":"","referenceNumber":"33","graphicNumbers":["2"],"alternatePartType":null,"modifier":{"name":"(17X36X12-MM THK)","language":"en"},"isCCRPart":false,"imageIdentifiers":["CM20210624-2d68b-3b790","CM20210624-c57f8-6c9d7","CM20210624-4607f-36df5","CM20210624-481f0-920fa"],"hasAlternate":false},{"noteCodes":" ","partNumber":"6H7062","orgCode":"CAT","partName":{"name":"SPACER","language":"en"},"serviceabilityIndicator":true,"partSequenceNumber":-913,"parentage":1,"quantity":"2","ieSystemControlNumber":null,"disambiguation":false,"mediaNumber":null,"componentId":null,"comments":"","referenceNumber":"34","graphicNumbers":["2","5"],"alternatePartType":null,"modifier":{"name":"(13.5X25X19-MM THK)","language":"en"},"isCCRPart":false,"imageIdentifiers":["CM20180404-39513-50297"],"hasAlternate":false},{"noteCodes":" ","partNumber":"6V1635","orgCode":"CAT","partName":{"name":"RIVET-POP","language":"en"},"serviceabilityIndicator":true,"partSequenceNumber":-912,"parentage":1,"quantity":"8","ieSystemControlNumber":null,"disambiguation":false,"mediaNumber":null,"componentId":null,"comments":"","referenceNumber":"35","graphicNumbers":["4","5"],"alternatePartType":null,"modifier":{"name":null,"language":"en"},"isCCRPart":false,"imageIdentifiers":["CM20201214-e9dea-ef0a7"],"hasAlternate":false},{"noteCodes":"M","partNumber":"2026473","orgCode":"CAT","partName":{"name":"BOLT","language":"en"},"serviceabilityIndicator":true,"partSequenceNumber":-911,"parentage":1,"quantity":"4","ieSystemControlNumber":null,"disambiguation":false,"mediaNumber":null,"componentId":null,"comments":"","referenceNumber":"36","graphicNumbers":["3"],"alternatePartType":"K","modifier":{"name":"(M16X2X60-MM)","language":"en"},"isCCRPart":false,"imageIdentifiers":["CM20180404-40474-30091"],"hasAlternate":true},{"noteCodes":"M","partNumber":"7X2556","orgCode":"CAT","partName":{"name":"BOLT","language":"en"},"serviceabilityIndicator":true,"partSequenceNumber":-910,"parentage":1,"quantity":"4","ieSystemControlNumber":null,"disambiguation":false,"mediaNumber":null,"componentId":null,"comments":"","referenceNumber":"37","graphicNumbers":["3"],"alternatePartType":null,"modifier":{"name":"(M16X2X100-MM)","language":"en"},"isCCRPart":false,"imageIdentifiers":["CM20201026-46859-fb3ae","CM20201026-ef672-81c08","CM20201026-2cc71-c8f7b","CM20201026-20241-0c6ab"],"hasAlternate":false},{"noteCodes":" ","partNumber":"7X7729","orgCode":"CAT","partName":{"name":"WASHER","language":"en"},"serviceabilityIndicator":true,"partSequenceNumber":-909,"parentage":1,"quantity":"22","ieSystemControlNumber":null,"disambiguation":false,"mediaNumber":null,"componentId":null,"comments":"","referenceNumber":"38","graphicNumbers":["2","3"],"alternatePartType":"K","modifier":{"name":"(11X25X3-MM THK)","language":"en"},"isCCRPart":false,"imageIdentifiers":["CM20210629-bad51-43939","CM20210414-221b3-f5794","CM20210629-25491-92260","CM20210629-c0b45-1d875"],"hasAlternate":true},{"noteCodes":"M","partNumber":"3445675","orgCode":"CAT","partName":{"name":"NUT","language":"en"},"serviceabilityIndicator":true,"partSequenceNumber":-908,"parentage":1,"quantity":"8","ieSystemControlNumber":null,"disambiguation":false,"mediaNumber":null,"componentId":null,"comments":"","referenceNumber":"39","graphicNumbers":["2"],"alternatePartType":null,"modifier":{"name":"(M10X1.5-THD)","language":"en"},"isCCRPart":false,"imageIdentifiers":["CM20210414-df391-00b7e","CM20210414-aae2b-3d618","CM20210414-1312c-b1012","CM20210414-2ef9a-55e19"],"hasAlternate":false},{"noteCodes":"M","partNumber":"8T4189","orgCode":"CAT","partName":{"name":"BOLT","language":"en"},"serviceabilityIndicator":true,"partSequenceNumber":-907,"parentage":1,"quantity":"8","ieSystemControlNumber":null,"disambiguation":false,"mediaNumber":null,"componentId":null,"comments":"","referenceNumber":"40","graphicNumbers":["2"],"alternatePartType":null,"modifier":{"name":"(M8X1.25X20-MM)","language":"en"},"isCCRPart":false,"imageIdentifiers":["CM20210414-24ddf-34ee7","CM20210527-231d2-7d865","CM20210512-e0e3e-bc0e3","CM20210512-e00dd-57fc9"],"hasAlternate":false},{"noteCodes":"CM","partNumber":"8T4193","orgCode":"CAT","partName":{"name":"BOLT","language":"en"},"serviceabilityIndicator":true,"partSequenceNumber":-906,"parentage":1,"quantity":"28","ieSystemControlNumber":null,"disambiguation":false,"mediaNumber":null,"componentId":null,"comments":"","referenceNumber":"41","graphicNumbers":["2"],"alternatePartType":null,"modifier":{"name":"(M16X2X50-MM)","language":"en"},"isCCRPart":false,"imageIdentifiers":["CM20180123-64731-45729","CM20180123-64731-54188","CM20180123-64731-55710","CM20180123-64731-54156"],"hasAlternate":false},{"noteCodes":"M","partNumber":"8T4195","orgCode":"CAT","partName":{"name":"BOLT","language":"en"},"serviceabilityIndicator":true,"partSequenceNumber":-905,"parentage":1,"quantity":"14","ieSystemControlNumber":null,"disambiguation":false,"mediaNumber":null,"componentId":null,"comments":"","referenceNumber":"42","graphicNumbers":["2","3"],"alternatePartType":null,"modifier":{"name":"(M10X1.5X30-MM)","language":"en"},"isCCRPart":false,"imageIdentifiers":["CM20210414-00c7f-7c9f3","CM20210414-33845-d6371","CM20210414-e00e1-21487","CM20210414-d1997-99d2d"],"hasAlternate":false},{"noteCodes":"M","partNumber":"1837121","orgCode":"CAT","partName":{"name":"BOLT","language":"en"},"serviceabilityIndicator":true,"partSequenceNumber":-904,"parentage":1,"quantity":"11","ieSystemControlNumber":null,"disambiguation":false,"mediaNumber":null,"componentId":null,"comments":"","referenceNumber":"43","graphicNumbers":["1","2"],"alternatePartType":null,"modifier":{"name":"(M10X1.5X35-MM)","language":"en"},"isCCRPart":false,"imageIdentifiers":["CM20210505-55aee-c8ada","CM20210505-052db-4c756","CM20210505-50850-98ed4","CM20210505-85deb-73042"],"hasAlternate":false},{"noteCodes":" ","partNumber":"8T4224","orgCode":"CAT","partName":{"name":"WASHER-HARD","language":"en"},"serviceabilityIndicator":true,"partSequenceNumber":-903,"parentage":1,"quantity":"18","ieSystemControlNumber":null,"disambiguation":false,"mediaNumber":null,"componentId":null,"comments":"","referenceNumber":"44","graphicNumbers":["2","3","4"],"alternatePartType":"K","modifier":{"name":"(8.8X16X2-MM THK)","language":"en"},"isCCRPart":false,"imageIdentifiers":["CM20210719-7e81c-47c33","CM20210719-2754b-b5cf7","CM20210719-79aea-8d775","CM20210719-2754b-b5cf7"],"hasAlternate":true},{"noteCodes":"M","partNumber":"8T4908","orgCode":"CAT","partName":{"name":"BOLT","language":"en"},"serviceabilityIndicator":true,"partSequenceNumber":-902,"parentage":1,"quantity":"6","ieSystemControlNumber":null,"disambiguation":false,"mediaNumber":null,"componentId":null,"comments":"","referenceNumber":"45","graphicNumbers":["3"],"alternatePartType":null,"modifier":{"name":"(M8X1.25X25-MM)","language":"en"},"isCCRPart":false,"imageIdentifiers":["CM20210527-59316-74784","CM20210527-c2b5a-51c9c","CM20210527-ed06e-164e2","CM20210527-cc32a-66dcc"],"hasAlternate":false},{"noteCodes":"M","partNumber":"8T4910","orgCode":"CAT","partName":{"name":"BOLT","language":"en"},"serviceabilityIndicator":true,"partSequenceNumber":-901,"parentage":1,"quantity":"6","ieSystemControlNumber":null,"disambiguation":false,"mediaNumber":null,"componentId":null,"comments":"","referenceNumber":"46","graphicNumbers":["2"],"alternatePartType":null,"modifier":{"name":"(M12X1.75X60-MM)","language":"en"},"isCCRPart":false,"imageIdentifiers":["CM20210504-8a3bc-d5338","CM20210504-893ee-52372","CM20210504-b28cf-9af63","CM20210504-b8307-f93c4"],"hasAlternate":false},{"noteCodes":"M","partNumber":"8T5005","orgCode":"CAT","partName":{"name":"BOLT","language":"en"},"serviceabilityIndicator":true,"partSequenceNumber":-900,"parentage":1,"quantity":"4","ieSystemControlNumber":null,"disambiguation":false,"mediaNumber":null,"componentId":null,"comments":"","referenceNumber":"47","graphicNumbers":["3"],"alternatePartType":null,"modifier":{"name":"(M10X1.5X70-MM)","language":"en"},"isCCRPart":false,"imageIdentifiers":["CM20210504-67891-f2dcb","CM20210504-14c1a-71628","CM20210504-74627-c69ca","CM20210504-7929e-2f1ec"],"hasAlternate":false},{"noteCodes":"M","partNumber":"8T6466","orgCode":"CAT","partName":{"name":"BOLT","language":"en"},"serviceabilityIndicator":true,"partSequenceNumber":-899,"parentage":1,"quantity":"4","ieSystemControlNumber":null,"disambiguation":false,"mediaNumber":null,"componentId":null,"comments":"","referenceNumber":"48","graphicNumbers":["1"],"alternatePartType":null,"modifier":{"name":"(M10X1.5X60-MM)","language":"en"},"isCCRPart":false,"imageIdentifiers":["CM20210503-c1bfb-337d3","CM20210503-b0350-eb9b8","CM20210503-332fc-7fcea","CM20210503-23de0-883be"],"hasAlternate":false},{"noteCodes":"M","partNumber":"8T7547","orgCode":"CAT","partName":{"name":"BOLT","language":"en"},"serviceabilityIndicator":true,"partSequenceNumber":-898,"parentage":1,"quantity":"4","ieSystemControlNumber":null,"disambiguation":false,"mediaNumber":null,"componentId":null,"comments":"","referenceNumber":"49","graphicNumbers":["4"],"alternatePartType":null,"modifier":{"name":"(M8X1.25X30-MM)","language":"en"},"isCCRPart":false,"imageIdentifiers":["CM20210503-8477e-c86d9","CM20210503-2645a-fb2b9","CM20210503-1353a-2326e","CM20210503-21204-6f0e5"],"hasAlternate":false},{"noteCodes":"M","partNumber":"8T8549","orgCode":"CAT","partName":{"name":"LOCKNUT","language":"en"},"serviceabilityIndicator":true,"partSequenceNumber":-897,"parentage":1,"quantity":"2","ieSystemControlNumber":null,"disambiguation":false,"mediaNumber":null,"componentId":null,"comments":"","referenceNumber":"50","graphicNumbers":["2","5"],"alternatePartType":null,"modifier":{"name":"(M12X1.75-THD)","language":"en"},"isCCRPart":false,"imageIdentifiers":["CM20180123-59674-13400","CM20180123-59674-09746","CM20180123-59674-40827","CM20180123-59674-64193"],"hasAlternate":false},{"noteCodes":"C","partNumber":"9X8257","orgCode":"CAT","partName":{"name":"WASHER","language":"en"},"serviceabilityIndicator":true,"partSequenceNumber":-896,"parentage":1,"quantity":"4","ieSystemControlNumber":null,"disambiguation":false,"mediaNumber":null,"componentId":null,"comments":"","referenceNumber":"51","graphicNumbers":["3"],"alternatePartType":"K","modifier":{"name":"(17.5X30X3.5-MM THK)","language":"en"},"isCCRPart":false,"imageIdentifiers":["CM20210414-e297c-89d42","CM20210414-90f06-bc7ee","CM20210414-31870-5cd7f","CM20210414-47ef9-49eaf"],"hasAlternate":true},{"noteCodes":" ","partNumber":"1L6377","orgCode":"CAT","partName":{"name":"BUTTON-PLUG","language":"en"},"serviceabilityIndicator":true,"partSequenceNumber":-895,"parentage":1,"quantity":"1","ieSystemControlNumber":null,"disambiguation":false,"mediaNumber":null,"componentId":null,"comments":"","referenceNumber":"52","graphicNumbers":["1"],"alternatePartType":null,"modifier":{"name":null,"language":"en"},"isCCRPart":false,"imageIdentifiers":["CM20230317-bf705-56d06","CM20230317-81b29-63d47","CM20230317-dd7ee-e4312","CM20230317-7fd63-7f23a"],"hasAlternate":false}],"notes":[{"noteCode":"C","note":{"name":"CHANGE FROM PREVIOUS TYPE","language":"en"}},{"noteCode":"M","note":{"name":"METRIC PART","language":"en"}}],"isExpandedMiningProduct":false}